rsmime-0.7.0.dist-info/METADATA
rsmime-0.7.0.dist-info/WHEEL
rsmime-0.7.0.dist-info/licenses/LICENSE.md
rsmime/__init__.py
rsmime/__init__.pyi
rsmime/exceptions/__init__.pyi
rsmime/rsmime.cpython-313t-aarch64-linux-gnu.so
rsmime-0.7.0.dist-info/RECORD
