Metadata-Version: 2.4
Name: rsmime
Version: 0.7.0
Classifier: License :: OSI Approved :: MIT License
Classifier: Development Status :: 3 - Alpha
Classifier: Intended Audience :: Developers
Classifier: Programming Language :: Python
Classifier: Programming Language :: Rust
Classifier: Operating System :: POSIX
Classifier: Operating System :: MacOS :: MacOS X
Requires-Dist: callee==0.3.1 ; extra == 'dev'
Requires-Dist: maturin==1.3.1 ; extra == 'dev'
Requires-Dist: mike==1.1.2 ; extra == 'dev'
Requires-Dist: mkdocs-autorefs==0.5.0 ; extra == 'dev'
Requires-Dist: mkdocs-material==9.4.7 ; extra == 'dev'
Requires-Dist: mkdocstrings[python]==0.23.0 ; extra == 'dev'
Requires-Dist: pytest==7.4.3 ; extra == 'dev'
Requires-Dist: ruff==0.1.3 ; extra == 'dev'
Provides-Extra: dev
License-File: LICENSE.md
Summary: Python package for signing and verifying S/MIME messages
